keymaster/__init__.py
keymaster/audit.py
keymaster/cli.py
keymaster/config.py
keymaster/db.py
keymaster/env.py
keymaster/providers.py
keymaster/security.py
keymaster/utils.py
keymaster-0.1.1.dist-info/LICENSE
keymaster-0.1.1.dist-info/METADATA
keymaster-0.1.1.dist-info/WHEEL
keymaster-0.1.1.dist-info/entry_points.txt
keymaster-0.1.1.dist-info/top_level.txt
keymaster-0.1.1.dist-info/RECORD
