Metadata-Version: 2.2
Name: keymaster
Version: 0.1.1
Summary: Secure API key management for the API services you use, including AI services.
Author-email: Joe Azure <jazure@gmail.com>
License: Apache-2.0
Project-URL: Homepage, https://github.com/joeazure/keymaster
Project-URL: Documentation, https://github.com/joeazure/keymaster#readme
Project-URL: Repository, https://github.com/joeazure/keymaster.git
Project-URL: Issues, https://github.com/joeazure/keymaster/issues
Keywords: security,api-keys,key-management,ai-services
Classifier: Development Status :: 4 - Beta
Classifier: Intended Audience :: Developers
Classifier: License :: OSI Approved :: Apache Software License
Classifier: Operating System :: OS Independent
Classifier: Programming Language :: Python :: 3
Classifier: Programming Language :: Python :: 3.11
Classifier: Topic :: Security
Classifier: Topic :: Software Development :: Libraries :: Python Modules
Requires-Python: >=3.11
License-File: LICENSE
Requires-Dist: click>=8.1.0
Requires-Dist: keyring>=24.0.0
Requires-Dist: pyyaml>=6.0.0
Requires-Dist: cryptography>=41.0.0
Requires-Dist: python-dotenv>=1.0.0
Requires-Dist: structlog>=23.0.0
Requires-Dist: requests>=2.31.0
Provides-Extra: test
Requires-Dist: pytest>=7.4.0; extra == "test"
Requires-Dist: pytest-cov>=4.1.0; extra == "test"
Requires-Dist: pytest-mock>=3.11.1; extra == "test"
Requires-Dist: responses>=0.23.0; extra == "test"
Requires-Dist: freezegun>=1.2.0; extra == "test"
